<?xml version="1.0" ?>
<!-- =================================================================================== -->
<!-- |    This document was autogenerated by xacro from mjcf_include/assets.xacro      | -->
<!-- |    EDITING THIS FILE BY HAND IS NOT RECOMMENDED                                 | -->
<!-- =================================================================================== -->
<mujoco>
  <!-- 2. Key base macros which build up the xml code snippets -->
  <!-- 3. Looping macros to repeatedly make xml snippets -->
  <!-- 4. Main macro, create code for all objects in yaml file -->
  <mesh file="models/cube/cube_fillet_45.STL" name="cube_fillet_45_normal_15" refquat="1 0 0 0" scale="0.6 0.6 0.6"/>
  <mesh file="models/cube/cube_fillet_45.STL" name="cube_fillet_45_normal_14" refquat="1 0 0 0" scale="0.657142857142857 0.657142857142857 0.657142857142857"/>
  <mesh file="models/cube/cube_fillet_45.STL" name="cube_fillet_45_normal_13" refquat="1 0 0 0" scale="0.7142857142857142 0.7142857142857142 0.7142857142857142"/>
  <mesh file="models/cube/cube_fillet_45.STL" name="cube_fillet_45_normal_12" refquat="1 0 0 0" scale="0.7714285714285714 0.7714285714285714 0.7714285714285714"/>
  <mesh file="models/cube/cube_fillet_45.STL" name="cube_fillet_45_normal_11" refquat="1 0 0 0" scale="0.8285714285714285 0.8285714285714285 0.8285714285714285"/>
  <mesh file="models/cube/cube_fillet_45.STL" name="cube_fillet_45_normal_10" refquat="1 0 0 0" scale="0.8857142857142857 0.8857142857142857 0.8857142857142857"/>
  <mesh file="models/cube/cube_fillet_45.STL" name="cube_fillet_45_normal_9" refquat="1 0 0 0" scale="0.9428571428571428 0.9428571428571428 0.9428571428571428"/>
  <mesh file="models/cube/cube_fillet_45.STL" name="cube_fillet_45_normal_8" refquat="1 0 0 0" scale="1.0 1.0 1.0"/>
  <mesh file="models/cube/cube_fillet_45.STL" name="cube_fillet_45_normal_7" refquat="1 0 0 0" scale="1.057142857142857 1.057142857142857 1.057142857142857"/>
  <mesh file="models/cube/cube_fillet_45.STL" name="cube_fillet_45_normal_6" refquat="1 0 0 0" scale="1.1142857142857143 1.1142857142857143 1.1142857142857143"/>
  <mesh file="models/cube/cube_fillet_45.STL" name="cube_fillet_45_normal_5" refquat="1 0 0 0" scale="1.1714285714285713 1.1714285714285713 1.1714285714285713"/>
  <mesh file="models/cube/cube_fillet_45.STL" name="cube_fillet_45_normal_4" refquat="1 0 0 0" scale="1.2285714285714284 1.2285714285714284 1.2285714285714284"/>
  <mesh file="models/cube/cube_fillet_45.STL" name="cube_fillet_45_normal_3" refquat="1 0 0 0" scale="1.2857142857142856 1.2857142857142856 1.2857142857142856"/>
  <mesh file="models/cube/cube_fillet_45.STL" name="cube_fillet_45_normal_2" refquat="1 0 0 0" scale="1.3428571428571427 1.3428571428571427 1.3428571428571427"/>
  <mesh file="models/cube/cube_fillet_45.STL" name="cube_fillet_45_normal_1" refquat="1 0 0 0" scale="1.4 1.4 1.4"/>
  <mesh file="models/cube/cube_fillet_35.STL" name="cube_fillet_35_normal_15" refquat="1 0 0 0" scale="0.6 0.6 0.6"/>
  <mesh file="models/cube/cube_fillet_35.STL" name="cube_fillet_35_normal_14" refquat="1 0 0 0" scale="0.657142857142857 0.657142857142857 0.657142857142857"/>
  <mesh file="models/cube/cube_fillet_35.STL" name="cube_fillet_35_normal_13" refquat="1 0 0 0" scale="0.7142857142857142 0.7142857142857142 0.7142857142857142"/>
  <mesh file="models/cube/cube_fillet_35.STL" name="cube_fillet_35_normal_12" refquat="1 0 0 0" scale="0.7714285714285714 0.7714285714285714 0.7714285714285714"/>
  <mesh file="models/cube/cube_fillet_35.STL" name="cube_fillet_35_normal_11" refquat="1 0 0 0" scale="0.8285714285714285 0.8285714285714285 0.8285714285714285"/>
  <mesh file="models/cube/cube_fillet_35.STL" name="cube_fillet_35_normal_10" refquat="1 0 0 0" scale="0.8857142857142857 0.8857142857142857 0.8857142857142857"/>
  <mesh file="models/cube/cube_fillet_35.STL" name="cube_fillet_35_normal_9" refquat="1 0 0 0" scale="0.9428571428571428 0.9428571428571428 0.9428571428571428"/>
  <mesh file="models/cube/cube_fillet_35.STL" name="cube_fillet_35_normal_8" refquat="1 0 0 0" scale="1.0 1.0 1.0"/>
  <mesh file="models/cube/cube_fillet_35.STL" name="cube_fillet_35_normal_7" refquat="1 0 0 0" scale="1.057142857142857 1.057142857142857 1.057142857142857"/>
  <mesh file="models/cube/cube_fillet_35.STL" name="cube_fillet_35_normal_6" refquat="1 0 0 0" scale="1.1142857142857143 1.1142857142857143 1.1142857142857143"/>
  <mesh file="models/cube/cube_fillet_35.STL" name="cube_fillet_35_normal_5" refquat="1 0 0 0" scale="1.1714285714285713 1.1714285714285713 1.1714285714285713"/>
  <mesh file="models/cube/cube_fillet_35.STL" name="cube_fillet_35_normal_4" refquat="1 0 0 0" scale="1.2285714285714284 1.2285714285714284 1.2285714285714284"/>
  <mesh file="models/cube/cube_fillet_35.STL" name="cube_fillet_35_normal_3" refquat="1 0 0 0" scale="1.2857142857142856 1.2857142857142856 1.2857142857142856"/>
  <mesh file="models/cube/cube_fillet_35.STL" name="cube_fillet_35_normal_2" refquat="1 0 0 0" scale="1.3428571428571427 1.3428571428571427 1.3428571428571427"/>
  <mesh file="models/cube/cube_fillet_35.STL" name="cube_fillet_35_normal_1" refquat="1 0 0 0" scale="1.4 1.4 1.4"/>
  <mesh file="models/cube/cube_fillet_25.STL" name="cube_fillet_25_normal_15" refquat="1 0 0 0" scale="0.6 0.6 0.6"/>
  <mesh file="models/cube/cube_fillet_25.STL" name="cube_fillet_25_normal_14" refquat="1 0 0 0" scale="0.657142857142857 0.657142857142857 0.657142857142857"/>
  <mesh file="models/cube/cube_fillet_25.STL" name="cube_fillet_25_normal_13" refquat="1 0 0 0" scale="0.7142857142857142 0.7142857142857142 0.7142857142857142"/>
  <mesh file="models/cube/cube_fillet_25.STL" name="cube_fillet_25_normal_12" refquat="1 0 0 0" scale="0.7714285714285714 0.7714285714285714 0.7714285714285714"/>
  <mesh file="models/cube/cube_fillet_25.STL" name="cube_fillet_25_normal_11" refquat="1 0 0 0" scale="0.8285714285714285 0.8285714285714285 0.8285714285714285"/>
  <mesh file="models/cube/cube_fillet_25.STL" name="cube_fillet_25_normal_10" refquat="1 0 0 0" scale="0.8857142857142857 0.8857142857142857 0.8857142857142857"/>
  <mesh file="models/cube/cube_fillet_25.STL" name="cube_fillet_25_normal_9" refquat="1 0 0 0" scale="0.9428571428571428 0.9428571428571428 0.9428571428571428"/>
  <mesh file="models/cube/cube_fillet_25.STL" name="cube_fillet_25_normal_8" refquat="1 0 0 0" scale="1.0 1.0 1.0"/>
  <mesh file="models/cube/cube_fillet_25.STL" name="cube_fillet_25_normal_7" refquat="1 0 0 0" scale="1.057142857142857 1.057142857142857 1.057142857142857"/>
  <mesh file="models/cube/cube_fillet_25.STL" name="cube_fillet_25_normal_6" refquat="1 0 0 0" scale="1.1142857142857143 1.1142857142857143 1.1142857142857143"/>
  <mesh file="models/cube/cube_fillet_25.STL" name="cube_fillet_25_normal_5" refquat="1 0 0 0" scale="1.1714285714285713 1.1714285714285713 1.1714285714285713"/>
  <mesh file="models/cube/cube_fillet_25.STL" name="cube_fillet_25_normal_4" refquat="1 0 0 0" scale="1.2285714285714284 1.2285714285714284 1.2285714285714284"/>
  <mesh file="models/cube/cube_fillet_25.STL" name="cube_fillet_25_normal_3" refquat="1 0 0 0" scale="1.2857142857142856 1.2857142857142856 1.2857142857142856"/>
  <mesh file="models/cube/cube_fillet_25.STL" name="cube_fillet_25_normal_2" refquat="1 0 0 0" scale="1.3428571428571427 1.3428571428571427 1.3428571428571427"/>
  <mesh file="models/cube/cube_fillet_25.STL" name="cube_fillet_25_normal_1" refquat="1 0 0 0" scale="1.4 1.4 1.4"/>
  <mesh file="models/cube/cube_fillet_15.STL" name="cube_fillet_15_normal_15" refquat="1 0 0 0" scale="0.6 0.6 0.6"/>
  <mesh file="models/cube/cube_fillet_15.STL" name="cube_fillet_15_normal_14" refquat="1 0 0 0" scale="0.657142857142857 0.657142857142857 0.657142857142857"/>
  <mesh file="models/cube/cube_fillet_15.STL" name="cube_fillet_15_normal_13" refquat="1 0 0 0" scale="0.7142857142857142 0.7142857142857142 0.7142857142857142"/>
  <mesh file="models/cube/cube_fillet_15.STL" name="cube_fillet_15_normal_12" refquat="1 0 0 0" scale="0.7714285714285714 0.7714285714285714 0.7714285714285714"/>
  <mesh file="models/cube/cube_fillet_15.STL" name="cube_fillet_15_normal_11" refquat="1 0 0 0" scale="0.8285714285714285 0.8285714285714285 0.8285714285714285"/>
  <mesh file="models/cube/cube_fillet_15.STL" name="cube_fillet_15_normal_10" refquat="1 0 0 0" scale="0.8857142857142857 0.8857142857142857 0.8857142857142857"/>
  <mesh file="models/cube/cube_fillet_15.STL" name="cube_fillet_15_normal_9" refquat="1 0 0 0" scale="0.9428571428571428 0.9428571428571428 0.9428571428571428"/>
  <mesh file="models/cube/cube_fillet_15.STL" name="cube_fillet_15_normal_8" refquat="1 0 0 0" scale="1.0 1.0 1.0"/>
  <mesh file="models/cube/cube_fillet_15.STL" name="cube_fillet_15_normal_7" refquat="1 0 0 0" scale="1.057142857142857 1.057142857142857 1.057142857142857"/>
  <mesh file="models/cube/cube_fillet_15.STL" name="cube_fillet_15_normal_6" refquat="1 0 0 0" scale="1.1142857142857143 1.1142857142857143 1.1142857142857143"/>
  <mesh file="models/cube/cube_fillet_15.STL" name="cube_fillet_15_normal_5" refquat="1 0 0 0" scale="1.1714285714285713 1.1714285714285713 1.1714285714285713"/>
  <mesh file="models/cube/cube_fillet_15.STL" name="cube_fillet_15_normal_4" refquat="1 0 0 0" scale="1.2285714285714284 1.2285714285714284 1.2285714285714284"/>
  <mesh file="models/cube/cube_fillet_15.STL" name="cube_fillet_15_normal_3" refquat="1 0 0 0" scale="1.2857142857142856 1.2857142857142856 1.2857142857142856"/>
  <mesh file="models/cube/cube_fillet_15.STL" name="cube_fillet_15_normal_2" refquat="1 0 0 0" scale="1.3428571428571427 1.3428571428571427 1.3428571428571427"/>
  <mesh file="models/cube/cube_fillet_15.STL" name="cube_fillet_15_normal_1" refquat="1 0 0 0" scale="1.4 1.4 1.4"/>
  <mesh file="models/cube/cube_fillet_5.STL" name="cube_fillet_5_normal_15" refquat="1 0 0 0" scale="0.6 0.6 0.6"/>
  <mesh file="models/cube/cube_fillet_5.STL" name="cube_fillet_5_normal_14" refquat="1 0 0 0" scale="0.657142857142857 0.657142857142857 0.657142857142857"/>
  <mesh file="models/cube/cube_fillet_5.STL" name="cube_fillet_5_normal_13" refquat="1 0 0 0" scale="0.7142857142857142 0.7142857142857142 0.7142857142857142"/>
  <mesh file="models/cube/cube_fillet_5.STL" name="cube_fillet_5_normal_12" refquat="1 0 0 0" scale="0.7714285714285714 0.7714285714285714 0.7714285714285714"/>
  <mesh file="models/cube/cube_fillet_5.STL" name="cube_fillet_5_normal_11" refquat="1 0 0 0" scale="0.8285714285714285 0.8285714285714285 0.8285714285714285"/>
  <mesh file="models/cube/cube_fillet_5.STL" name="cube_fillet_5_normal_10" refquat="1 0 0 0" scale="0.8857142857142857 0.8857142857142857 0.8857142857142857"/>
  <mesh file="models/cube/cube_fillet_5.STL" name="cube_fillet_5_normal_9" refquat="1 0 0 0" scale="0.9428571428571428 0.9428571428571428 0.9428571428571428"/>
  <mesh file="models/cube/cube_fillet_5.STL" name="cube_fillet_5_normal_8" refquat="1 0 0 0" scale="1.0 1.0 1.0"/>
  <mesh file="models/cube/cube_fillet_5.STL" name="cube_fillet_5_normal_7" refquat="1 0 0 0" scale="1.057142857142857 1.057142857142857 1.057142857142857"/>
  <mesh file="models/cube/cube_fillet_5.STL" name="cube_fillet_5_normal_6" refquat="1 0 0 0" scale="1.1142857142857143 1.1142857142857143 1.1142857142857143"/>
  <mesh file="models/cube/cube_fillet_5.STL" name="cube_fillet_5_normal_5" refquat="1 0 0 0" scale="1.1714285714285713 1.1714285714285713 1.1714285714285713"/>
  <mesh file="models/cube/cube_fillet_5.STL" name="cube_fillet_5_normal_4" refquat="1 0 0 0" scale="1.2285714285714284 1.2285714285714284 1.2285714285714284"/>
  <mesh file="models/cube/cube_fillet_5.STL" name="cube_fillet_5_normal_3" refquat="1 0 0 0" scale="1.2857142857142856 1.2857142857142856 1.2857142857142856"/>
  <mesh file="models/cube/cube_fillet_5.STL" name="cube_fillet_5_normal_2" refquat="1 0 0 0" scale="1.3428571428571427 1.3428571428571427 1.3428571428571427"/>
  <mesh file="models/cube/cube_fillet_5.STL" name="cube_fillet_5_normal_1" refquat="1 0 0 0" scale="1.4 1.4 1.4"/>
</mujoco>

