<mujoco><body name="cuboid_311_fillet_15_thinner_6" pos="0 0 0">
    <inertial diaginertia="4.151882812500001e-05 0.0006112494140625001 0.0006112494140625001" mass="0.05467500000000001" pos="0 0 0" quat="1 0 0 0"/>
    <freejoint name="cuboid_311_fillet_15_thinner_6"/>
    <geom mesh="cuboid_311_fillet_15_thinner_6" name="cuboid_311_fillet_15_thinner_6_geom" type="mesh"/>
  </body>
  <body name="cuboid_221_fillet_5_normal_3" pos="0 0 0">
    <inertial diaginertia="3.973642985026041e-05 6.357828776041666e-05 3.973642985026041e-05" mass="0.0244140625" pos="0 0 0" quat="0.7071 0.7071 0 0"/>
    <freejoint name="cuboid_221_fillet_5_normal_3"/>
    <geom mesh="cuboid_221_fillet_5_normal_3" name="cuboid_221_fillet_5_normal_3_geom" type="mesh"/>
  </body>
  <body name="cuboid_211_fillet_45_normal_5" pos="0 0 0">
    <inertial diaginertia="3.9550781250000015e-05 9.887695312500003e-05 9.887695312500003e-05" mass="0.0421875" pos="0 0 0" quat="1 0 0 0"/>
    <freejoint name="cuboid_211_fillet_45_normal_5"/>
    <geom mesh="cuboid_211_fillet_45_normal_5" name="cuboid_211_fillet_45_normal_5_geom" type="mesh"/>
  </body>
  <body name="cylinder_12_fillet_25_upright_13" pos="0 0 0">
    <inertial diaginertia="0.00024278463994417015 0.00024278463994417015 1.0933572544178026e-05" mass="0.023179883381924202" pos="0 0 0" quat="0 0.01 0 0"/>
    <freejoint name="cylinder_12_fillet_25_upright_13"/>
    <geom mesh="cylinder_12_fillet_25_upright_13" name="cylinder_12_fillet_25_upright_13_geom" type="mesh"/>
  </body>
  <body name="sphere_normal_17" pos="0 0 0">
    <inertial diaginertia="0.00037976965964318926 0.00037976965964318926 0.00037976965964318926" mass="0.2226958681050274" pos="0 0 0" quat="1 0 0 0"/>
    <freejoint name="sphere_normal_17"/>
    <geom mesh="sphere_normal_17" name="sphere_normal_17_geom" type="mesh"/>
  </body>
  <body name="cylinder_13_fillet_15_sideways_14" pos="0 0 0">
    <inertial diaginertia="0.00037861697182419335 0.00037861697182419335 1.15842013535097e-05" mass="0.023997922740524782" pos="0 0 0" quat="0.683 0.683 0.183 0.183"/>
    <freejoint name="cylinder_13_fillet_15_sideways_14"/>
    <geom mesh="cylinder_13_fillet_15_sideways_14" name="cylinder_13_fillet_15_sideways_14_geom" type="mesh"/>
  </body>
  <body name="cylinder_12_fillet_5_upright_14" pos="0 0 0">
    <inertial diaginertia="0.00023162710577523187 0.00023162710577523187 1.0312511911424553e-05" mass="0.022380648688046643" pos="0 0 0" quat="0 0.01 0 0"/>
    <freejoint name="cylinder_12_fillet_5_upright_14"/>
    <geom mesh="cylinder_12_fillet_5_upright_14" name="cylinder_12_fillet_5_upright_14_geom" type="mesh"/>
  </body>
  <body name="cylinder_14_fillet_25_normal_4" pos="0 0 0">
    <inertial diaginertia="0.001651438943266059 0.001651438943266059 5.0956447548361555e-05" mass="0.05836782069970846" pos="0 0 0" quat="0.683 0.683 0.183 0.183"/>
    <freejoint name="cylinder_14_fillet_25_normal_4"/>
    <geom mesh="cylinder_14_fillet_25_normal_4" name="cylinder_14_fillet_25_normal_4_geom" type="mesh"/>
  </body>
  <body name="cuboid_211_fillet_5_upright_7" pos="0 0 0">
    <inertial diaginertia="8.38807291666667e-06 2.0970182291666673e-05 2.0970182291666673e-05" mass="0.016637500000000003" pos="0 0 0" quat="0.707 0 0.707 0"/>
    <freejoint name="cuboid_211_fillet_5_upright_7"/>
    <geom mesh="cuboid_211_fillet_5_upright_7" name="cuboid_211_fillet_5_upright_7_geom" type="mesh"/>
  </body>
  <body name="cylinder_11_fillet_15_normal_11" pos="0 0 0">
    <inertial diaginertia="0.0005836556249999998 0.0005836556249999998 7.381124999999998e-05" mass="0.07289999999999998" pos="0 0 0" quat="1 0 0 0"/>
    <freejoint name="cylinder_11_fillet_15_normal_11"/>
    <geom mesh="cylinder_11_fillet_15_normal_11" name="cylinder_11_fillet_15_normal_11_geom" type="mesh"/>
  </body>
  <body name="cylinder_12_fillet_15_sideways_6" pos="0 0 0">
    <inertial diaginertia="0.0016316114769515673 0.0016316114769515673 0.0001163229122538228" mass="0.09577521865889212" pos="0 0 0" quat="0.683 0.683 0.183 0.183"/>
    <freejoint name="cylinder_12_fillet_15_sideways_6"/>
    <geom mesh="cylinder_12_fillet_15_sideways_6" name="cylinder_12_fillet_15_sideways_6_geom" type="mesh"/>
  </body>
  <body name="cube_fillet_15_normal_2" pos="0 0 0">
    <inertial diaginertia="0.000727776147240237 0.000727776147240237 0.000727776147240237" mass="0.24215276967930024" pos="0 0 0" quat="1 0 0 0"/>
    <freejoint name="cube_fillet_15_normal_2"/>
    <geom mesh="cube_fillet_15_normal_2" name="cube_fillet_15_normal_2_geom" type="mesh"/>
  </body>
  <body name="cuboid_211_fillet_5_normal_7" pos="0 0 0">
    <inertial diaginertia="2.3354340820312507e-05 5.8385852050781267e-05 5.8385852050781267e-05" mass="0.030754687500000006" pos="0 0 0" quat="1 0 0 0"/>
    <freejoint name="cuboid_211_fillet_5_normal_7"/>
    <geom mesh="cuboid_211_fillet_5_normal_7" name="cuboid_211_fillet_5_normal_7_geom" type="mesh"/>
  </body>
  <body name="cylinder_12_fillet_25_sideways_4" pos="0 0 0">
    <inertial diaginertia="0.0022845967035684538 0.0022845967035684538 0.00017649244920271318" mass="0.12299562682215744" pos="0 0 0" quat="0.683 0.683 0.183 0.183"/>
    <freejoint name="cylinder_12_fillet_25_sideways_4"/>
    <geom mesh="cylinder_12_fillet_25_sideways_4" name="cylinder_12_fillet_25_sideways_4_geom" type="mesh"/>
  </body>
  <body name="sphere_normal_70" pos="0 0 0">
    <inertial diaginertia="9.709322266185959e-05 9.709322266185959e-05 9.709322266185959e-05" mass="0.09824565438632198" pos="0 0 0" quat="1 0 0 0"/>
    <freejoint name="sphere_normal_70"/>
    <geom mesh="sphere_normal_70" name="sphere_normal_70_geom" type="mesh"/>
  </body>
  <body name="cylinder_11_fillet_5_normal_5" pos="0 0 0">
    <inertial diaginertia="0.0018835199999999996 0.0018835199999999996 0.00031103999999999995" mass="0.17279999999999998" pos="0 0 0" quat="1 0 0 0"/>
    <freejoint name="cylinder_11_fillet_5_normal_5"/>
    <geom mesh="cylinder_11_fillet_5_normal_5" name="cylinder_11_fillet_5_normal_5_geom" type="mesh"/>
  </body>
  <body name="cuboid_211_fillet_15_normal_6" pos="0 0 0">
    <inertial diaginertia="3.060364059448244e-05 7.650910148620609e-05 7.650910148620609e-05" mass="0.03617050781250001" pos="0 0 0" quat="1 0 0 0"/>
    <freejoint name="cuboid_211_fillet_15_normal_6"/>
    <geom mesh="cuboid_211_fillet_15_normal_6" name="cuboid_211_fillet_15_normal_6_geom" type="mesh"/>
  </body>
  <body name="cylinder_21_fillet_25_normal_7" pos="0 0 0">
    <inertial diaginertia="0.000222144696852502 0.000222144696852502 7.580292973165945e-05" mass="0.032242565597667645" pos="0 0 0" quat="1 0 0 0"/>
    <freejoint name="cylinder_21_fillet_25_normal_7"/>
    <geom mesh="cylinder_21_fillet_25_normal_7" name="cylinder_21_fillet_25_normal_7_geom" type="mesh"/>
  </body>
  <body name="cylinder_11_fillet_35_normal_7" pos="0 0 0">
    <inertial diaginertia="0.0013207402083333325 0.0013207402083333325 0.00020131374999999988" mass="0.13309999999999994" pos="0 0 0" quat="1 0 0 0"/>
    <freejoint name="cylinder_11_fillet_35_normal_7"/>
    <geom mesh="cylinder_11_fillet_35_normal_7" name="cylinder_11_fillet_35_normal_7_geom" type="mesh"/>
  </body>
  <body name="sphere_normal_23" pos="0 0 0">
    <inertial diaginertia="0.00033114953447847204 0.00033114953447847204 0.00033114953447847204" mass="0.20512306126602886" pos="0 0 0" quat="1 0 0 0"/>
    <freejoint name="sphere_normal_23"/>
    <geom mesh="sphere_normal_23" name="sphere_normal_23_geom" type="mesh"/>
  </body>
  <body name="ground" pos="0 0 0">
    <geom name="ground_geom" size="1 1 1" type="plane"/>
  </body>
</mujoco>